telegram_error_notifications/__init__.py
telegram_error_notifications/admin.py
telegram_error_notifications/apps.py
telegram_error_notifications/handlers.py
telegram_error_notifications/models.py
telegram_error_notifications/settings.py
telegram_error_notifications/urls.py
telegram_error_notifications/utils.py
telegram_error_notifications/views.py
telegram_error_notifications/management/__init__.py
telegram_error_notifications/management/commands/__init__.py
telegram_error_notifications/management/commands/create_telegram_bot.py
telegram_error_notifications/migrations/0001_initial.py
telegram_error_notifications/migrations/__init__.py
telegram_error_notifications/templates/telegram_technical_500.txt
django_telegram_error_notifications-0.0.2.dist-info/LICENSE
django_telegram_error_notifications-0.0.2.dist-info/METADATA
django_telegram_error_notifications-0.0.2.dist-info/WHEEL
django_telegram_error_notifications-0.0.2.dist-info/top_level.txt
django_telegram_error_notifications-0.0.2.dist-info/RECORD
