Metadata-Version: 2.1
Name: django-telegram-error-notifications
Version: 0.0.2
Summary: A Django app to send errors to telegram bot.
Home-page: https://github.com/nocl1p/django-telegram-error-notifications
Author: Igor Lysenko
Author-email: wishyoumarryfriday@gmail.com
License: MIT
Platform: UNKNOWN
Classifier: Development Status :: 4 - Beta
Classifier: License :: OSI Approved :: MIT License
Classifier: Programming Language :: Python :: 3.4
Classifier: Programming Language :: Python :: 3.6
Classifier: Programming Language :: Python :: 3.7
Classifier: Programming Language :: Python :: 3.8
